.DS_Store
pMTnet_Omni/__init__.py
pMTnet_Omni/__main__.py
pMTnet_Omni/background_tcr_loaders.py
pMTnet_Omni/classifier.py
pMTnet_Omni/pMTnet_Omni_class.py
pMTnet_Omni/utilities.py
pMTnet_Omni/encoders/__init__.py
pMTnet_Omni/encoders/cdr3_alpha_encoder_model.py
pMTnet_Omni/encoders/cdr3_beta_encoder_model.py
pMTnet_Omni/encoders/encoder_class.py
pMTnet_Omni/encoders/pmhc_encoder_class.py
pMTnet_Omni/encoders/pmhc_encoder_model.py
pMTnet_Omni/encoders/tcr_encoder_class.py
pMTnet_Omni/encoders/utilities.py
pMTnet_Omni/encoders/v_alpha_encoder_model.py
pMTnet_Omni/encoders/v_beta_encoder_model.py
pMTnet_Omni-0.0.3.dist-info/LICENSE
pMTnet_Omni-0.0.3.dist-info/METADATA
pMTnet_Omni-0.0.3.dist-info/WHEEL
pMTnet_Omni-0.0.3.dist-info/top_level.txt
pMTnet_Omni-0.0.3.dist-info/RECORD
